Metadata-Version: 1.0
Name: ich-distributions
Version: 0.1
Summary: Gaussian distributions
Home-page: UNKNOWN
Author: lchh
Author-email: UNKNOWN
License: UNKNOWN
Platform: UNKNOWN
